noteline/__init__.py
noteline/noteline_notebook.py
noteline/core/__init__.py
noteline/core/envs.py
noteline/core/noteline_notebook.py
noteline_sdk_core-2.2.4.dist-info/LICENSE
noteline_sdk_core-2.2.4.dist-info/METADATA
noteline_sdk_core-2.2.4.dist-info/WHEEL
noteline_sdk_core-2.2.4.dist-info/top_level.txt
noteline_sdk_core-2.2.4.dist-info/RECORD
