Metadata-Version: 2.1
Name: noteline-sdk-core
Version: 2.2.4
Summary: core Noteline SDK
Home-page: https://github.com/noteline-org/noteline-core
Author: Viacheslav Kovalevskyi
Author-email: viacheslav@kovalevskyi.com
License: UNKNOWN
Platform: UNKNOWN
Classifier: Programming Language :: Python :: 3
Classifier: License :: OSI Approved :: MIT License
Classifier: Operating System :: OS Independent
Requires-Python: >=3.6
Requires-Dist: nbformat
Requires-Dist: smart-open
